{
  "general": {
    "internal_job": "2025-026",
    "symphony": "9999999",
    "project_name": "CASSI",
    "project_type": "CLT",
    "clients": [
      "TÂN HIỆP PHÁT"
    ],
    "project_objectives": "Mục tiêu: Đánh giá sản phầm và bảng mô tả ý tưởng bánh snack (vị bò)",
    "platform": "iField",
    "interview_methods": [
      "CATI"
    ],
    "recruit_methods": [
      "FW free find/ FW connection"
    ],
    "type_of_quota_control": "No Quota",
    "quota_description": [],
    "service_line": "INNO",
    "provinces": [
      "Hồ Chí Minh",
      "Hà Nội"
    ],
    "industries": [
      "Thực phẩm - Đồ ăn nhẹ"
    ],
    "target_audiences": [
      {
        "age_group": [
          0,
          0
        ],
        "audience_id": "ID0000002",
        "comment": {},
        "complexity": "Basic",
        "description": "",
        "extra_rate": 0,
        "gender": "Both",
        "household_income": [
          0,
          0
        ],
        "incident_rate": 100,
        "industry_name": "Thực phẩm - Đồ ăn nhẹ",
        "pricing": [
          {
            "comment": {},
            "price": 115000,
            "price_growth": 0,
            "type": "recruit"
          },
          {
            "comment": {},
            "price": 41000,
            "price_growth": 0,
            "type": "location"
          }
        ],
        "sample_size": 100,
        "sample_type": "Main",
        "target": {
          "daily_interview_target": 55,
          "daily_sup_target": 3.33,
          "interviewers_per_supervisor": 10,
          "target_for_interviewer": 3
        },
        "target_audience_name": "Người dùng Sản phẩm bánh Snack"
      }
    ],
    "interview_length": 54,
    "questionnaire_length": 0,
    "device_type": "Tablet < 9 inch",
    "tablet_usage_duration": "<= 15 phút",
    "bw_page_count": 10,
    "showphoto_page_count": 0,
    "showcard_page_count": 10,
    "dropcard_page_count": 0,
    "color_page_count": 0,
    "decal_page_count": 0,
    "laminated_page_count": 0,
    "interview_form_package_count": 0,
    "stimulus_material_production_count": 0,
    "scripting": false,
    "data_processing": false,
    "coding": false,
    "data_entry": false,
    "open_ended_main_count": 0,
    "open_ended_booster_count": 0,
    "data_processing_method": [],
    "sampling_method": "Purposive sampling",
    "recruit_method": [
      "FW free find/ FW connection"
    ]
  },
  "sampling_methods": [
    {
      "sample_type": "Main",
      "sampling_method": "Purposive sampling"
    },
    {
      "description": "Uống Heneiken Silver thường xuyên nhất.",
      "sample_type": "Booster",
      "sampling_method": "Purposive sampling"
    }
  ],
  "clt_settings": {
    "clt_test_products": 3,
    "clt_respondent_visits": 1,
    "clt_sample_usage_details": "Rót 300ml,uống tí nhất 100ml...",
    "clt_number_of_samples_to_label": 2,
    "clt_description_howtolabelthesample": "Yêu cầu về dán mẫu",
    "clt_sample_split_method": "Yêu cầu về chiết mẫu",
    "clt_preparation_steps": "Ướp mẫu, giặt đồ.",
    "clt_supplies_required": "Mua cân",
    "clt_sample_delivery_method": "",
    "clt_other_requirements": "Nhận xét 8",
    "clt_return_unused_samples": "Yes",
    "clt_return_used_samples": "Yes",
    "clt_total_concepts": 2,
    "clt_concepts_per_respondent": 1,
    "print_concept_laminated_in_plastic": false,
    "print_concept_in_black_white": true,
    "print_concept_in_color": false,
    "print_showphoto": true,
    "print_showdrop": true,
    "clt_dan_mau_days": 0,
    "clt_sample_size_per_day": 65,
    "clt_desk_interviewers_count": 0,
    "clt_provincial_desk_interviewers_count": 0,
    "clt_assistant_setup_days": 1,
    "clt_failure_rate": 10,
    "clt_sample_recruit_idi": 5
  },
  "hut_settings": {
    "hut_test_products": 0,
    "hut_usage_duration": 0
  },
  "cost_toggles": {
    "device_rental_costs": {
      "Chi phí thuê tablet < 9 inch": true,
      "Chi phí thuê tablet >= 9 inch": false,
      "Chi phí thuê laptop": false
    },
    "idi_costs": {
      "Chi phí Tuyển đáp viên IDI": true,
      "Chi phí Quản lý IDI": true,
      "Chi phí QC - IDI": true,
      "Quà Phiếu PV - IDI": true
    },
    "failure_rate_costs": {
      "Chi phí Phiếu PV - Bài rớt giữa chừng": true
    },
    "qc_method_costs": {
      "Chi phí QC - In home": false,
      "Chi phí QC - In Location": false,
      "Chi phí QC - DP": false,
      "Chi phí thuê laptop": false,
      "Chi phí Quản lý - On-field": false
    },
    "qc_communication_costs": {
      "Chi phí Card điện thoại": true
    },
    "dp_costs": {
      "Chi phí Coding": false,
      "Chi phí Input": false,
      "Chi phí Quản lý - On-field": false
    },
    "incentive_costs": {
      "Quà Phiếu PV - Pilot": false,
      "Quà Phiếu PV - Main": false,
      "Quà Phiếu PV - Booster": false,
      "Quà Phiếu PV - Non": false
    },
    "stationary_costs": {
      "Photo trắng đen": true,
      "Showphoto": false,
      "Showcard": true,
      "Dropcard": false,
      "In màu \\ In concept": false,
      "Decal": false,
      "Ép Plastic": false,
      "Hồ sơ biểu mẫu": false,
      "Chi phí đóng cuốn": false
    }
  },
  "settings": {
    "interviewers_per_supervisor": 10,
    "parking_fee": 5000,
    "distant_district_fee": 5000,
    "stationary": {
      "Hồ Chí Minh": {
        "bw_page_fee": 350,
        "showphoto_page_fee": 2500,
        "showcard_page_fee": 4000,
        "dropcard_page_fee": 9000,
        "color_page_fee": 2500,
        "decal_page_fee": 3500,
        "laminated_page_fee": 6000,
        "interview_form_package_fee": 350,
        "stimulus_material_production_fee": 4000
      },
      "Hà Nội": {
        "bw_page_fee": 400,
        "showphoto_page_fee": 3000,
        "showcard_page_fee": 6000,
        "dropcard_page_fee": 9000,
        "color_page_fee": 3000,
        "decal_page_fee": 2500,
        "laminated_page_fee": 5000,
        "interview_form_package_fee": 400,
        "stimulus_material_production_fee": 4000
      },
      "Đà Nẵng": {
        "bw_page_fee": 450,
        "showphoto_page_fee": 2500,
        "showcard_page_fee": 4000,
        "dropcard_page_fee": 9000,
        "color_page_fee": 3500,
        "decal_page_fee": 3500,
        "laminated_page_fee": 7000,
        "interview_form_package_fee": 450,
        "stimulus_material_production_fee": 4000
      },
      "Cần Thơ": {
        "bw_page_fee": 400,
        "showphoto_page_fee": 2500,
        "showcard_page_fee": 3500,
        "dropcard_page_fee": 9000,
        "color_page_fee": 2500,
        "decal_page_fee": 3500,
        "laminated_page_fee": 6000,
        "interview_form_package_fee": 400,
        "stimulus_material_production_fee": 4000
      },
      "Others": {
        "bw_page_fee": 350,
        "showphoto_page_fee": 2500,
        "showcard_page_fee": 4000,
        "dropcard_page_fee": 9000,
        "color_page_fee": 2500,
        "decal_page_fee": 3500,
        "laminated_page_fee": 6000,
        "interview_form_package_fee": 400,
        "stimulus_material_production_fee": 4000
      }
    },
    "transportation": {
      "Others": {
        "flight": 1000000,
        "train": 400000
      }
    },
    "travel_junior_hotel": 500000,
    "travel_junior_food": 500000,
    "travel_senior_hotel": 1000000,
    "travel_senior_food": 800000,
    "travel_manager_hotel": 2000000,
    "travel_manager_food": 1000000,
    "travel_director_hotel": 3000000,
    "travel_director_food": 1200000
  },
  "samples": {
    "Hồ Chí Minh": {
      "Main - Người dùng Sản phẩm bánh Snack": {
        "age_group": [
          0,
          0
        ],
        "audience_id": "ID0000002",
        "comment": {},
        "complexity": "Basic",
        "description": "",
        "extra_rate": 0,
        "gender": "Both",
        "household_income": [
          0,
          0
        ],
        "incident_rate": 100,
        "industry_name": "Thực phẩm - Đồ ăn nhẹ",
        "pricing": [
          {
            "comment": {},
            "price": 115000,
            "price_growth": 0,
            "type": "recruit"
          },
          {
            "comment": {},
            "price": 41000,
            "price_growth": 0,
            "type": "location"
          }
        ],
        "sample_size": 100,
        "sample_type": "Main",
        "target": {
          "daily_interview_target": 55,
          "daily_sup_target": 3.33,
          "interviewers_per_supervisor": 10,
          "target_for_interviewer": 3
        },
        "target_audience_name": "Người dùng Sản phẩm bánh Snack"
      }
    },
    "Hà Nội": {
      "Main - Người dùng Sản phẩm bánh Snack": {
        "age_group": [
          0,
          0
        ],
        "audience_id": "ID0000002",
        "comment": {},
        "complexity": "Basic",
        "description": "",
        "extra_rate": 0,
        "gender": "Both",
        "household_income": [
          0,
          0
        ],
        "incident_rate": 100,
        "industry_name": "Thực phẩm - Đồ ăn nhẹ",
        "pricing": [
          {
            "comment": {},
            "price": 115000,
            "price_growth": 0,
            "type": "recruit"
          },
          {
            "comment": {},
            "price": 41000,
            "price_growth": 0,
            "type": "location"
          }
        ],
        "sample_size": 100,
        "sample_type": "Main",
        "target": {
          "daily_interview_target": 55,
          "daily_sup_target": 3.33,
          "interviewers_per_supervisor": 10,
          "target_for_interviewer": 3
        },
        "target_audience_name": "Người dùng Sản phẩm bánh Snack"
      }
    }
  },
  "qc_methods": [],
  "travel": {
    "Hồ Chí Minh": {
      "fulltime": {
        "travel_days": 0,
        "travel_nights": 0,
        "assigned_people": []
      },
      "parttime": {
        "supervisor": {
          "distant": 0,
          "nearby": 0,
          "recruit_distant": 0,
          "recruit_nearby": 0,
          "ngoi_ban_distant": 0,
          "ngoi_ban_nearby": 0
        },
        "interviewer": {
          "distant": 0,
          "nearby": 0,
          "recruit_distant": 0,
          "recruit_nearby": 0,
          "ngoi_ban_distant": 0,
          "ngoi_ban_nearby": 0
        },
        "qc": {
          "distant": 0,
          "nearby": 0
        }
      }
    },
    "Hà Nội": {
      "fulltime": {
        "travel_days": 0,
        "travel_nights": 0,
        "assigned_people": []
      },
      "parttime": {
        "supervisor": {
          "distant": 0,
          "nearby": 0,
          "recruit_distant": 0,
          "recruit_nearby": 0,
          "ngoi_ban_distant": 0,
          "ngoi_ban_nearby": 0
        },
        "interviewer": {
          "distant": 0,
          "nearby": 0,
          "recruit_distant": 0,
          "recruit_nearby": 0,
          "ngoi_ban_distant": 0,
          "ngoi_ban_nearby": 0
        },
        "qc": {
          "distant": 0,
          "nearby": 0
        }
      }
    }
  },
  "assignments": [],
  "additional_costs": [],
  "subcontracts": [
    {
      "cost_type": "Scripting link",
      "currency": "USD",
      "optional_detail": "",
      "subcontractor": "External Subcontract",
      "unit": 1,
      "unit_cost": 100
    }
  ]
}